<?xml version="1.0" encoding="UTF-8"?>

<databaseChangeLog
        xmlns="http://www.liquibase.org/xml/ns/dbchangelog"
        xmlns:xsi="http://www.w3.org/2001/XMLSchema-instance"
        xsi:schemaLocation="http://www.liquibase.org/xml/ns/dbchangelog
         http://www.liquibase.org/xml/ns/dbchangelog/dbchangelog-3.1.xsd">

        <include file="create-user-table.xml"
                 relativeToChangelogFile="true"/>
        <include file="create-list-table.xml"
                 relativeToChangelogFile="true"/>
        <include file="create-product-table.xml"
                 relativeToChangelogFile="true"/>
        <include file="create-listcontent-table.xml"
                 relativeToChangelogFile="true"/>
        <include file="create-role-table.xml"
                 relativeToChangelogFile="true"/>
        <include file="create-permission-table.xml"
                 relativeToChangelogFile="true"/>
        <include file="insert-role-table.xml"
                 relativeToChangelogFile="true"/>
        <include file="alter-product-table.xml"
                 relativeToChangelogFile="true"/>
        <include file="alter-created-fields.xml"
                 relativeToChangelogFile="true"/>
        <include file="standarize-tables.xml"
                 relativeToChangelogFile="true"/>
</databaseChangeLog>